mdml_client/MDML_client.py
mdml_client/__init__.py
mdml_client/config.py
mdml_client-1.2.15.dist-info/LICENSE
mdml_client-1.2.15.dist-info/METADATA
mdml_client-1.2.15.dist-info/WHEEL
mdml_client-1.2.15.dist-info/top_level.txt
mdml_client-1.2.15.dist-info/RECORD
