Metadata-Version: 2.1
Name: mdml-client
Version: 1.2.15
Summary: Client to connect to the MDML
Home-page: https://github.com/anl-mdml/MDML_Client
Author: Jakob Elias
Author-email: jelias@anl.gov
License: UNKNOWN
Platform: UNKNOWN
Classifier: Programming Language :: Python :: 3
Classifier: License :: OSI Approved :: MIT License
Classifier: Operating System :: OS Independent
Requires-Dist: pandas
Requires-Dist: boto3
Requires-Dist: confluent-kafka
Requires-Dist: requests
Requires-Dist: jsonschema
